README
setup.py
bambu_signup/__init__.py
bambu_signup/forms.py
bambu_signup/models.py
bambu_signup/urls.py
bambu_signup.egg-info/PKG-INFO
bambu_signup.egg-info/SOURCES.txt
bambu_signup.egg-info/dependency_links.txt
bambu_signup.egg-info/requires.txt
bambu_signup.egg-info/top_level.txt
bambu_signup/migrations/0001_initial.py
bambu_signup/migrations/__init__.py
bambu_signup/templates/signup/complete.html
bambu_signup/templates/signup/forgot-password.html
bambu_signup/templates/signup/form.inc.html
bambu_signup/templates/signup/login.html
bambu_signup/templates/signup/password-reset.html
bambu_signup/templates/signup/register.html
bambu_signup/templates/signup/validation.html
bambu_signup/templates/signup/mail/password-reset.txt
bambu_signup/templates/signup/mail/password.txt
bambu_signup/templates/signup/mail/validate.txt
bambu_signup/views/__init__.py
bambu_signup/views/ajax.py