Metadata-Version: 1.1
Name: bambu-signup
Version: 2.0
Summary: A fluid signup method for free web apps
Home-page: http://pypi.python.org/pypi/bambu-formatrules
Author: Steadman
Author-email: mark@steadman.io
License: UNKNOWN
Platform: UNKNOWN
Classifier: Development Status :: 4 - Beta
Classifier: Environment :: Web Environment
Classifier: Framework :: Django
